Workbook

Sheet Instructions
A1: 04 | Automotive Component Business Case
A3: Purpose | B3: Translate the selected strategy into an illustrative capacity and investment case.
A4: Base strategy | B4: Focused automotive-component manufacturing platform with phased capacity build.
A5: Currency | B5: ₹ crore unless otherwise stated.
A6: Planning horizon | B6: 2027–2036.
A7: Core flow | B7: Addressable demand → capacity → utilization → revenue → EBITDA → CAPEX → free cash flow → returns.
A8: Important | B8: All company-specific operating assumptions are synthetic case assumptions.

Sheet Assumptions
A1: Business Case Assumptions
A3: Assumption | B3: Value | C3: Unit | D3: Type | E3: Rationale / note
A4: Addressable market in 2027 | B4: 35000 | C4: ₹ crore | D4: Synthetic | E4: Illustrative SAM for selected component opportunity
A5: Market growth | B5: 9 | C5: % CAGR | D5: Synthetic | E5: Linked to market research case assumption
A6: Target attainable share in 2031 | B6: 8 | C6: % of SAM | D6: Synthetic | E6: Long-run share assumption
A7: Initial capacity utilization | B7: 35 | C7: % | D7: Synthetic | E7: Ramp-up assumption
A8: Mature capacity utilization | B8: 80 | C8: % | D8: Synthetic | E8: Steady-state assumption
A9: Average selling price | B9: 1.2 | C9: ₹ lakh / unit | D9: Synthetic | E9: Illustrative blended component ASP
A10: Variable cost | B10: 0.78 | C10: ₹ lakh / unit | D10: Synthetic | E10: Materials + direct variable conversion
A11: Fixed operating cost | B11: 45 | C11: ₹ crore / year | D11: Synthetic | E11: Plant + staff + quality + overhead
A12: Initial CAPEX | B12: 220 | C12: ₹ crore | D12: Synthetic | E12: Land/building/equipment/tooling
A13: Expansion CAPEX | B13: 140 | C13: ₹ crore | D13: Synthetic | E13: Second-stage capacity investment
A14: Maintenance CAPEX | B14: 15 | C14: ₹ crore / year | D14: Synthetic | E14: Sustaining investment
A15: Tax rate | B15: 25 | C15: % | D15: Synthetic | E15: Simplified case assumption
... A17: Terminal growth | B17: 3 | C17: % | D17: Synthetic | E17: Used only for terminal value scenario

Sheet Demand
A1: Addressable Demand & Revenue Build
A3: Year | B3: Market ₹cr | C3: Target Share % | D3: Addressable Revenue Pool ₹cr | E3: Implied Units mn
A4: 2027 | B4: =Assumptions!B4 | C4: =MIN(Assumptions!B6,(2%+(ROW()-4)*1%)) | D4: =B4*C4 | E4: =D4/(Assumptions!B9/100)
A5: 2028 | B5: =B4*(1+Assumptions!B5/100) | C5: =MIN(Assumptions!B6,(2%+(ROW()-4)*1%)) | D5: =B5*C5 | E5: =D5/(Assumptions!B9/100)
A6: 2029 | B6: =B5*(1+Assumptions!B5/100) | C6: =MIN(Assumptions!B6,(2%+(ROW()-4)*1%)) | D6: =B6*C6 | E6: =D6/(Assumptions!B9/100)
A7: 2030 | B7: =B6*(1+Assumptions!B5/100) | C7: =MIN(Assumptions!B6,(2%+(ROW()-4)*1%)) | D7: =B7*C7 | E7: =D7/(Assumptions!B9/100)
A8: 2031 | B8: =B7*(1+Assumptions!B5/100) | C8: =MIN(Assumptions!B6,(2%+(ROW()-4)*1%)) | D8: =B8*C8 | E8: =D8/(Assumptions!B9/100)
A9: 2032 | B9: =B8*(1+Assumptions!B5/100) | C9: =MIN(Assumptions!B6,(2%+(ROW()-4)*1%)) | D9: =B9*C9 | E9: =D9/(Assumptions!B9/100)
A10: 2033 | B10: =B9*(1+Assumptions!B5/100) | C10: =MIN(Assumptions!B6,(2%+(ROW()-4)*1%)) | D10: =B10*C10 | E10: =D10/(Assumptions!B9/100)
A11: 2034 | B11: =B10*(1+Assumptions!B5/100) | C11: =MIN(Assumptions!B6,(2%+(ROW()-4)*1%)) | D11: =B11*C11 | E11: =D11/(Assumptions!B9/100)
A12: 2035 | B12: =B11*(1+Assumptions!B5/100) | C12: =MIN(Assumptions!B6,(2%+(ROW()-4)*1%)) | D12: =B12*C12 | E12: =D12/(Assumptions!B9/100)
A13: 2036 | B13: =B12*(1+Assumptions!B5/100) | C13: =MIN(Assumptions!B6,(2%+(ROW()-4)*1%)) | D13: =B13*C13 | E13: =D13/(Assumptions!B9/100)

Sheet Capacity
A1: Capacity & Utilization Plan
A3: Year | B3: Installed Capacity mn units | C3: Utilization % | D3: Production mn units | E3: Revenue ₹cr | F3: Expansion CAPEX ₹cr
A4: 2027 | B4: =0.25 | C4: =MIN(Assumptions!B8,35%+(ROW()-4)*5%) | D4: =B4*C4 | E4: =D4*Assumptions!B9 | F4: =0
A5: 2028 | B5: =0.25 | C5: =MIN(Assumptions!B8,35%+(ROW()-4)*5%) | D5: =B5*C5 | E5: =D5*Assumptions!B9 | F5: =0
A6: 2029 | B6: =0.25 | C6: =MIN(Assumptions!B8,35%+(ROW()-4)*5%) | D6: =B6*C6 | E6: =D6*Assumptions!B9 | F6: =0
A7: 2030 | B7: =0.25 | C7: =MIN(Assumptions!B8,35%+(ROW()-4)*5%) | D7: =B7*C7 | E7: =D7*Assumptions!B9 | F7: =0
A8: 2031 | B8: =0.50 | C8: =MIN(Assumptions!B8,35%+(ROW()-4)*5%) | D8: =B8*C8 | E8: =D8*Assumptions!B9 | F8: =Assumptions!B13
A9: 2032 | B9: =0.50 | C9: =MIN(Assumptions!B8,35%+(ROW()-4)*5%) | D9: =B9*C9 | E9: =D9*Assumptions!B9 | F9: =0
A10: 2033 | B10: =0.50 | C10: =MIN(Assumptions!B8,35%+(ROW()-4)*5%) | D10: =B10*C10 | E10: =D10*Assumptions!B9 | F10: =0
A11: 2034 | B11: =0.50 | C11: =MIN(Assumptions!B8,35%+(ROW()-4)*5%) | D11: =B11*C11 | E11: =D11*Assumptions!B9 | F11: =0
A12: 2035 | B12: =0.50 | C12: =MIN(Assumptions!B8,35%+(ROW()-4)*5%) | D12: =B12*C12 | E12: =D12*Assumptions!B9 | F12: =0
A13: 2036 | B13: =0.50 | C13: =MIN(Assumptions!B8,35%+(ROW()-4)*5%) | D13: =B13*C13 | E13: =D13*Assumptions!B9 | F13: =0

Sheet P_and_L
A1: Illustrative Operating Model
A3: Year | B3: Revenue ₹cr | C3: Variable Cost ₹cr | D3: Gross Contribution ₹cr | E3: Fixed Cost ₹cr | F3: EBITDA ₹cr | G3: EBITDA Margin
A4: 2027 | B4: =Capacity!E4 | C4: =Capacity!D4*Assumptions!B10 | D4: =B4-C4 | E4: =Assumptions!B11 | F4: =D4-E4 | G4: =IFERROR(F4/B4,0)
A5: 2028 | B5: =Capacity!E5 | C5: =Capacity!D5*Assumptions!B10 | D5: =B5-C5 | E5: =Assumptions!B11 | F5: =D5-E5 | G5: =IFERROR(F5/B5,0)
A6: 2029 | B6: =Capacity!E6 | C6: =Capacity!D6*Assumptions!B10 | D6: =B6-C6 | E6: =Assumptions!B11 | F6: =D6-E6 | G6: =IFERROR(F6/B6,0)
A7: 2030 | B7: =Capacity!E7 | C7: =Capacity!D7*Assumptions!B10 | D7: =B7-C7 | E7: =Assumptions!B11 | F7: =D7-E7 | G7: =IFERROR(F7/B7,0)
A8: 2031 | B8: =Capacity!E8 | C8: =Capacity!D8*Assumptions!B10 | D8: =B8-C8 | E8: =Assumptions!B11 | F8: =D8-E8 | G8: =IFERROR(F8/B8,0)
A9: 2032 | B9: =Capacity!E9 | C9: =Capacity!D9*Assumptions!B10 | D9: =B9-C9 | E9: =Assumptions!B11 | F9: =D9-E9 | G9: =IFERROR(F9/B9,0)
A10: 2033 | B10: =Capacity!E10 | C10: =Capacity!D10*Assumptions!B10 | D10: =B10-C10 | E10: =Assumptions!B11 | F10: =D10-E10 | G10: =IFERROR(F10/B10,0)
A11: 2034 | B11: =Capacity!E11 | C11: =Capacity!D11*Assumptions!B10 | D11: =B11-C11 | E11: =Assumptions!B11 | F11: =D11-E11 | G11: =IFERROR(F11/B11,0)
A12: 2035 | B12: =Capacity!E12 | C12: =Capacity!D12*Assumptions!B10 | D12: =B12-C12 | E12: =Assumptions!B11 | F12: =D12-E12 | G12: =IFERROR(F12/B12,0)
A13: 2036 | B13: =Capacity!E13 | C13: =Capacity!D13*Assumptions!B10 | D13: =B13-C13 | E13: =Assumptions!B11 | F13: =D13-E13 | G13: =IFERROR(F13/B13,0)

Sheet Cash_Flow
A1: Project Cash Flow
A3: Year | B3: EBITDA ₹cr | C3: Tax ₹cr | D3: Maintenance CAPEX ₹cr | E3: Expansion CAPEX ₹cr | F3: Initial CAPEX ₹cr | G3: Free Cash Flow ₹cr | H3: Cumulative FCF ₹cr
A4: 2027 | B4: =P_and_L!F4 | C4: =MAX(0,B4*Assumptions!B15) | D4: =Assumptions!B14 | E4: =Capacity!F4 | F4: =Assumptions!B12 | G4: =B4-C4-D4-E4-F4 | H4: =G4
A5: 2028 | B5: =P_and_L!F5 | C5: =MAX(0,B5*Assumptions!B15) | D5: =Assumptions!B14 | E5: =Capacity!F5 | F5: =0 | G5: =B5-C5-D5-E5-F5 | H5: =H4+G5
A6: 2029 | B6: =P_and_L!F6 | C6: =MAX(0,B6*Assumptions!B15) | D6: =Assumptions!B14 | E6: =Capacity!F6 | F6: =0 | G6: =B6-C6-D6-E6-F6 | H6: =H5+G6
A7: 2030 | B7: =P_and_L!F7 | C7: =MAX(0,B7*Assumptions!B15) | D7: =Assumptions!B14 | E7: =Capacity!F7 | F7: =0 | G7: =B7-C7-D7-E7-F7 | H7: =H6+G7
A8: 2031 | B8: =P_and_L!F8 | C8: =MAX(0,B8*Assumptions!B15) | D8: =Assumptions!B14 | E8: =Capacity!F8 | F8: =0 | G8: =B8-C8-D8-E8-F8 | H8: =H7+G8
A9: 2032 | B9: =P_and_L!F9 | C9: =MAX(0,B9*Assumptions!B15) | D9: =Assumptions!B14 | E9: =Capacity!F9 | F9: =0 | G9: =B9-C9-D9-E9-F9 | H9: =H8+G9
A10: 2033 | B10: =P_and_L!F10 | C10: =MAX(0,B10*Assumptions!B15) | D10: =Assumptions!B14 | E10: =Capacity!F10 | F10: =0 | G10: =B10-C10-D10-E10-F10 | H10: =H9+G10
A11: 2034 | B11: =P_and_L!F11 | C11: =MAX(0,B11*Assumptions!B15) | D11: =Assumptions!B14 | E11: =Capacity!F11 | F11: =0 | G11: =B11-C11-D11-E11-F11 | H11: =H10+G11
A12: 2035 | B12: =P_and_L!F12 | C12: =MAX(0,B12*Assumptions!B15) | D12: =Assumptions!B14 | E12: =Capacity!F12 | F12: =0 | G12: =B12-C12-D12-E12-F12 | H12: =H11+G12
A13: 2036 | B13: =P_and_L!F13 | C13: =MAX(0,B13*Assumptions!B15) | D13: =Assumptions!B14 | E13: =Capacity!F13 | F13: =0 | G13: =B13-C13-D13-E13-F13 | H13: =H12+G13

Sheet Returns
A1: Investment Returns
A3: Metric | B3: Value | C3: Interpretation
A4: Total revenue 2027–2036 | B4: =SUM(P_and_L!B4:B13) | C4: Cumulative revenue
A5: Peak annual revenue | B5: =MAX(P_and_L!B4:B13) | C5: Highest modeled annual revenue
A6: Peak EBITDA | B6: =MAX(P_and_L!F4:F13) | C6: Highest modeled EBITDA
A7: Total CAPEX | B7: =SUM(Cash_Flow!D4:F13) | C7: Initial + expansion + maintenance
A8: Cumulative FCF | B8: =Cash_Flow!H13 | C8: End-period cumulative project FCF
A9: NPV @ discount rate | B9: =NPV(Assumptions!B16,Cash_Flow!G4:G13) | C9: Simplified project NPV
A10: IRR | B10: =IRR(Cash_Flow!G4:G13) | C10: Unlevered project IRR proxy
A11: Payback year | B11: =IFERROR(INDEX(Cash_Flow!A4:A13,MATCH(TRUE,INDEX(Cash_Flow!H4:H13>=0,0),0)),"Beyond 2036") | C11: First year cumulative FCF turns positive

Sheet Scenarios
A1: Demand Scenario Analysis
A3: Scenario | B3: Market Growth | C3: Target Share Multiplier | D3: Capacity Utilization Multiplier | E3: Revenue Multiplier | F3: Interpretation
A4: Downside | B4: 7 | C4: 0.75 | D4: 0.85 | E4: =C4*D4 | F4: Slower market + lower share/utilization
A5: Base | B5: 9 | C5: 1 | D5: 1 | E5: =C5*D5 | F5: Base planning case
A6: Upside | B6: 11 | C6: 1.2 | D6: 1.1 | E6: =C6*D6 | F6: Higher market + stronger share/utilization

Sheet Sensitivity
A1: Illustrative NPV Sensitivity
A3: NPV sensitivity to utilization and ASP
A4: Utilization \ ASP | B4: 1 | C4: 1.1 | D4: 1.2 | E4: 1.3 | F4: 1.4
A5: 0.6 | B5: =Returns!B9*((($B/1.20)*($A5/0.80))-1)+Returns!B9 | C5: =Returns!B9*((($C/1.20)*($A5/0.80))-1)+Returns!B9 | D5: =Returns!B9*((($D/1.20)*($A5/0.80))-1)+Returns!B9 | E5: =Returns!B9*((($E/1.20)*($A5/0.80))-1)+Returns!B9 | F5: =Returns!B9*((($F/1.20)*($A5/0.80))-1)+Returns!B9
A6: 0.65 | B6: =Returns!B9*((($B/1.20)*($A6/0.80))-1)+Returns!B9 | C6: =Returns!B9*((($C/1.20)*($A6/0.80))-1)+Returns!B9 | D6: =Returns!B9*((($D/1.20)*($A6/0.80))-1)+Returns!B9 | E6: =Returns!B9*((($E/1.20)*($A6/0.80))-1)+Returns!B9 | F6: =Returns!B9*((($F/1.20)*($A6/0.80))-1)+Returns!B9
A7: 0.7 | B7: =Returns!B9*((($B/1.20)*($A7/0.80))-1)+Returns!B9 | C7: =Returns!B9*((($C/1.20)*($A7/0.80))-1)+Returns!B9 | D7: =Returns!B9*((($D/1.20)*($A7/0.80))-1)+Returns!B9 | E7: =Returns!B9*((($E/1.20)*($A7/0.80))-1)+Returns!B9 | F7: =Returns!B9*((($F/1.20)*($A7/0.80))-1)+Returns!B9
A8: 0.75 | B8: =Returns!B9*((($B/1.20)*($A8/0.80))-1)+Returns!B9 | C8: =Returns!B9*((($C/1.20)*($A8/0.80))-1)+Returns!B9 | D8: =Returns!B9*((($D/1.20)*($A8/0.80))-1)+Returns!B9 | E8: =Returns!B9*((($E/1.20)*($A8/0.80))-1)+Returns!B9 | F8: =Returns!B9*((($F/1.20)*($A8/0.80))-1)+Returns!B9
A9: 0.8 | B9: =Returns!B9*((($B/1.20)*($A9/0.80))-1)+Returns!B9 | C9: =Returns!B9*((($C/1.20)*($A9/0.80))-1)+Returns!B9 | D9: =Returns!B9*((($D/1.20)*($A9/0.80))-1)+Returns!B9 | E9: =Returns!B9*((($E/1.20)*($A9/0.80))-1)+Returns!B9 | F9: =Returns!B9*((($F/1.20)*($A9/0.80))-1)+Returns!B9
A11: Note | B11: Sensitivity is directional and intended for screening; detailed transaction-grade sensitivity should be rebuilt after validated pricing, utilization and cost inputs.

Sheet Validation_Checks
A1: Model Checks
A3: Check | B3: Test | C3: Status
A4: Demand growth linked | B4: =IF(Demand!B5=Demand!B4*(1+Assumptions!B5/100),"PASS","CHECK")
A5: Revenue linked to capacity | B5: =IF(P_and_L!B4=Capacity!E4,"PASS","CHECK")
A6: EBITDA formula | B6: =IF(P_and_L!F4=P_and_L!D4-P_and_L!E4,"PASS","CHECK")
A7: Cash flow formula | B7: =IF(Cash_Flow!G4=Cash_Flow!B4-Cash_Flow!C4-Cash_Flow!D4-Cash_Flow!E4-Cash_Flow!F4,"PASS","CHECK")
A8: Model sheets present | B8: =IF(COUNTA(Assumptions!A4:A17)>0,"PASS","CHECK")
